pr_clt/__init__.py
pr_clt/pr_clt.py
pr_clt-1.0.0.dist-info/DESCRIPTION.rst
pr_clt-1.0.0.dist-info/METADATA
pr_clt-1.0.0.dist-info/RECORD
pr_clt-1.0.0.dist-info/WHEEL
pr_clt-1.0.0.dist-info/entry_points.txt
pr_clt-1.0.0.dist-info/metadata.json
pr_clt-1.0.0.dist-info/top_level.txt
