Metadata-Version: 2.0
Name: pr-clt
Version: 1.0.0
Summary: Command Line Tool that searches for Pull Requests in Bitbucket account
Home-page: https://bitbucket.org/erik31/pullrequest-clt/
Author: Erik Duisheev
Author-email: duisheev_e@auca.kg
License: UNLICENSE
Platform: UNKNOWN
